dist_files/Dockerfile
dist_files/__init__.py
listener/__init__.py
listener/listener.py
super_simple_test_sequencer-0.14.8.data/scripts/super_simple_test_runner.py
test_definition_template/__init__.py
test_definition_template/common/Dockerfile
test_definition_template/common/__init__.py
test_definition_template/common/common_definitions.py
test_definition_template/common/init_deinit.py
test_definition_template/common/instruments.py
test_definition_template/common/logging.yaml
test_definition_template/common/test_report_writer.py
test_definition_template/example_sequence/__init__.py
test_definition_template/example_sequence/limits.py
test_definition_template/example_sequence/test_cases.py
test_definition_template/example_sequence/test_definition.py
test_runner/__init__.py
test_runner/exceptions.py
test_runner/runner.py
test_runner/test_case.py
ui/__init__.py
ui/build/asset-manifest.json
ui/build/index.html
ui/build/service-worker.js
ui/build/app/favicon.ico
ui/build/app/manifest.json
ui/build/i18n/en/applications.json
ui/build/i18n/en/diagnostics.json
ui/build/i18n/en/home.json
ui/build/i18n/en/login.json
ui/build/i18n/en/main.json
ui/build/i18n/en/manual-usage.json
ui/build/i18n/en/navigation.json
ui/build/i18n/en/robot.json
ui/build/i18n/zh/applications.json
ui/build/i18n/zh/diagnostics.json
ui/build/i18n/zh/login.json
ui/build/i18n/zh/main.json
ui/build/i18n/zh/manual-usage.json
ui/build/i18n/zh/navigation.json
ui/build/i18n/zh/robot.json
ui/build/routes/index.json
ui/build/routes/index2.json
ui/build/routes/index3.json
ui/build/static/css/main.89a2a648.css
ui/build/static/css/main.89a2a648.css.map
ui/build/static/css/main.d262d0f6.css
ui/build/static/css/main.d262d0f6.css.map
ui/build/static/js/0.541f45a8.chunk.js
ui/build/static/js/0.541f45a8.chunk.js.map
ui/build/static/js/0.ccc26ae4.chunk.js
ui/build/static/js/0.ccc26ae4.chunk.js.map
ui/build/static/js/main.35e4c515.js
ui/build/static/js/main.35e4c515.js.map
ui/build/static/js/main.60ae19b1.js
super_simple_test_sequencer-0.14.8.dist-info/LICENSE
super_simple_test_sequencer-0.14.8.dist-info/METADATA
super_simple_test_sequencer-0.14.8.dist-info/WHEEL
super_simple_test_sequencer-0.14.8.dist-info/top_level.txt
super_simple_test_sequencer-0.14.8.dist-info/RECORD
