Metadata-Version: 2.1
Name: super-simple-test-sequencer
Version: 0.14.8
Summary: Super simple test sequencer for production testing
Home-page: https://www.jotautomation.com
Author: JOT Automation Ltd.
Author-email: rami.rahikkala@jotautomation.com
License: MIT License
Platform: UNKNOWN
Classifier: Programming Language :: Python :: 3
Classifier: License :: OSI Approved :: MIT License
Classifier: Operating System :: OS Independent
Requires-Dist: PyYAML
Requires-Dist: colorama
Requires-Dist: coloredlogs
Requires-Dist: gaiaclient
Requires-Dist: json2html
Requires-Dist: tornado
Requires-Dist: wheel
